cornac/__init__.py
cornac/exception.py
cornac/hyperopt.py
cornac/data/__init__.py
cornac/data/dataset.py
cornac/data/graph.py
cornac/data/image.py
cornac/data/modality.py
cornac/data/reader.py
cornac/data/sentiment.py
cornac/data/text.py
cornac/datasets/__init__.py
cornac/datasets/amazon_clothing.py
cornac/datasets/amazon_digital_music.py
cornac/datasets/amazon_office.py
cornac/datasets/amazon_toy.py
cornac/datasets/citeulike.py
cornac/datasets/epinions.py
cornac/datasets/filmtrust.py
cornac/datasets/gowalla.py
cornac/datasets/movielens.py
cornac/datasets/netflix.py
cornac/datasets/tafeng.py
cornac/datasets/tradesy.py
cornac/datasets/yoochoose.py
cornac/eval_methods/__init__.py
cornac/eval_methods/base_method.py
cornac/eval_methods/cross_validation.py
cornac/eval_methods/next_basket_evaluation.py
cornac/eval_methods/next_item_evaluation.py
cornac/eval_methods/propensity_stratified_evaluation.py
cornac/eval_methods/ratio_split.py
cornac/eval_methods/stratified_split.py
cornac/experiment/__init__.py
cornac/experiment/experiment.py
cornac/experiment/result.py
cornac/metrics/__init__.py
cornac/metrics/ranking.py
cornac/metrics/rating.py
cornac/models/__init__.py
cornac/models/recommender.py
cornac/models/amr/__init__.py
cornac/models/amr/recom_amr.py
cornac/models/ann/__init__.py
cornac/models/ann/recom_ann_annoy.py
cornac/models/ann/recom_ann_base.py
cornac/models/ann/recom_ann_faiss.py
cornac/models/ann/recom_ann_hnswlib.py
cornac/models/ann/recom_ann_scann.py
cornac/models/baseline_only/__init__.py
cornac/models/baseline_only/recom_bo.cpython-311-x86_64-linux-gnu.so
cornac/models/beacon/__init__.py
cornac/models/beacon/beacon_tf.py
cornac/models/beacon/recom_beacon.py
cornac/models/bivaecf/__init__.py
cornac/models/bivaecf/bivae.py
cornac/models/bivaecf/recom_bivaecf.py
cornac/models/bpr/__init__.py
cornac/models/bpr/recom_bpr.cpython-311-x86_64-linux-gnu.so
cornac/models/bpr/recom_wbpr.cpython-311-x86_64-linux-gnu.so
cornac/models/c2pf/__init__.py
cornac-2.3.0.dist-info/AUTHORS
cornac-2.3.0.dist-info/LICENSE
cornac-2.3.0.dist-info/METADATA
cornac-2.3.0.dist-info/WHEEL
cornac-2.3.0.dist-info/top_level.txt
cornac-2.3.0.dist-info/RECORD
