Metadata-Version: 2.1
Name: cornac
Version: 2.3.0
Summary: A Comparative Framework for Multimodal Recommender Systems
Home-page: https://cornac.preferred.ai
Keywords: recommender system,collaborative filtering,multimodal,preference learning,recommendation
Classifier: Development Status :: 5 - Production/Stable
Classifier: Intended Audience :: Science/Research
Classifier: Intended Audience :: Education
Classifier: Intended Audience :: Developers
Classifier: Programming Language :: Python :: 3
Classifier: Programming Language :: Python :: 3.8
Classifier: Programming Language :: Python :: 3.9
Classifier: Programming Language :: Python :: 3.10
Classifier: Programming Language :: Python :: 3.11
Classifier: Programming Language :: Python :: 3.12
Classifier: License :: OSI Approved :: Apache Software License
Classifier: Topic :: Software Development
Classifier: Topic :: Scientific/Engineering
License-File: LICENSE
License-File: AUTHORS
Requires-Dist: numpy<2.0.0
Requires-Dist: scipy<=1.13.1
Requires-Dist: tqdm
Requires-Dist: powerlaw
Provides-Extra: tests
Requires-Dist: pytest; extra == "tests"
Requires-Dist: pytest-pep8; extra == "tests"
Requires-Dist: pytest-xdist; extra == "tests"
Requires-Dist: pytest-cov; extra == "tests"
Requires-Dist: Flask; extra == "tests"
